{
  "id": "admin-guide/permissions-and-roles",
  "title": "Permissions and Roles",
  "description": "Purpose",
  "source": "@site/docs/admin-guide/permissions-and-roles.md",
  "sourceDirName": "admin-guide",
  "slug": "/admin-guide/permissions-and-roles",
  "permalink": "/admin-guide/permissions-and-roles",
  "draft": false,
  "unlisted": false,
  "editUrl": "https://github.com/Turin-orient/User-manual/tree/main/docs/admin-guide/permissions-and-roles.md",
  "tags": [],
  "version": "current",
  "sidebarPosition": 3,
  "frontMatter": {
    "sidebar_position": 3
  },
  "sidebar": "tutorialSidebar",
  "previous": {
    "title": "User Management",
    "permalink": "/admin-guide/managing-users"
  },
  "next": {
    "title": "API Keys Overview",
    "permalink": "/admin-guide/api-keys-overview"
  }
}