{
  "id": "admin-guide/managing-users",
  "title": "User Management",
  "description": "This guide will help you manage all user accounts in your system. We have designed this \"step-by-step\" tutorial so that anyone, even without technical knowledge, can easily follow along.",
  "source": "@site/docs/admin-guide/managing-users.md",
  "sourceDirName": "admin-guide",
  "slug": "/admin-guide/managing-users",
  "permalink": "/admin-guide/managing-users",
  "draft": false,
  "unlisted": false,
  "editUrl": "https://github.com/Turin-orient/User-manual/tree/main/docs/admin-guide/managing-users.md",
  "tags": [],
  "version": "current",
  "sidebarPosition": 2,
  "frontMatter": {
    "id": "managing-users",
    "title": "User Management",
    "sidebar_label": "User Management",
    "sidebar_position": 2
  },
  "sidebar": "tutorialSidebar",
  "previous": {
    "title": "Admin Dashboard",
    "permalink": "/admin-guide/admin-dashboard"
  },
  "next": {
    "title": "Permissions and Roles",
    "permalink": "/admin-guide/permissions-and-roles"
  }
}